tornado_jsonapi/__init__.py
tornado_jsonapi/_schemas.py
tornado_jsonapi/exceptions.py
tornado_jsonapi/handlers.py
tornado_jsonapi/resource.py
tornado_jsonapi-0.1.4.dist-info/LICENSE
tornado_jsonapi-0.1.4.dist-info/METADATA
tornado_jsonapi-0.1.4.dist-info/WHEEL
tornado_jsonapi-0.1.4.dist-info/top_level.txt
tornado_jsonapi-0.1.4.dist-info/zip-safe
tornado_jsonapi-0.1.4.dist-info/RECORD
