Metadata-Version: 2.1
Name: tornado-jsonapi
Version: 0.1.4
Summary: Framework providing REST JSON API to Tornado web server
Home-page: http://github.com/lockie/tornado_jsonapi
Author: Andrew Kravchuk
Author-email: awkravchuk@gmail.com
License: MIT License
Keywords: tornado JSON API REST SQLAlchemy DBAPI
Platform: any
Classifier: Programming Language :: Python
Classifier: Development Status :: 4 - Beta
Classifier: Environment :: Web Environment
Classifier: Intended Audience :: Developers
Classifier: License :: OSI Approved :: MIT License
Classifier: Programming Language :: Python
Classifier: Programming Language :: Python :: 3.3
Classifier: Programming Language :: Python :: 3.4
Classifier: Programming Language :: Python :: 3.5
Classifier: Topic :: Software Development :: Libraries :: Application Frameworks
Classifier: Topic :: Internet :: WWW/HTTP :: Dynamic Content
Requires-Dist: accept (==0.1.0)
Requires-Dist: jsl (==0.2.2)
Requires-Dist: python-jsonschema-objects (==0.0.19.post2)
Requires-Dist: python-status (==1.0.1)
Requires-Dist: tornado (<6.0,>=4.2)
Provides-Extra: dbapi2
Requires-Dist: antiorm (==1.2.0) ; extra == 'dbapi2'
Provides-Extra: sqlalchemy
Requires-Dist: SQLAlchemy (==1.0.12) ; extra == 'sqlalchemy'
Requires-Dist: alchemyjsonschema (>=0.6.1) ; extra == 'sqlalchemy'
